{"nodes":[{"data":{"id":"ent_butler_volmer_equation","name":"Butler-Volmer Equation","type":"equation","domains":["00_foundations"]}},{"data":{"id":"ent_method_thermal_simulation","name":"Thermal Simulation","type":"method","domains":["02_components","08_software_middleware"]}},{"data":{"id":"ent_ficks_law","name":"Fick's law","type":"principle","domains":["00_foundations"]}},{"data":{"id":"ent_principle_conservation_of_charge","name":"Conservation of Charge","type":"principle","domains":["00_foundations"]}},{"data":{"id":"ent_foundation_electrochemistry","name":"Electrochemistry","type":"foundation","domains":["00_foundations"]}},{"data":{"id":"ent_method_equivalent_circuit_battery_model","name":"Equivalent-Circuit Battery Model","type":"method","domains":["02_components","06_design_engineering","00_foundations"]}}],"edges":[{"data":{"id":"rel_ent_method_equivalent_circuit_battery_model_has_prerequisite_ent_foundation_electrochemistry","source":"ent_method_equivalent_circuit_battery_model","target":"ent_foundation_electrochemistry","type":"has_prerequisite","description":"ent_method_equivalent_circuit_battery_model has_prerequisite ent_foundation_electrochemistry for interpreting polarization and diffusion parameters."}},{"data":{"id":"rel_ent_principle_conservation_of_charge_has_prerequisite_ent_foundation_electrochemistry","source":"ent_principle_conservation_of_charge","target":"ent_foundation_electrochemistry","type":"has_prerequisite","description":"ent_principle_conservation_of_charge has_prerequisite ent_foundation_electrochemistry for understanding ionic and electronic transport balances."}},{"data":{"id":"rel_ent_foundation_electrochemistry_uses_ent_ficks_law","source":"ent_foundation_electrochemistry","target":"ent_ficks_law","type":"uses","description":"Electrochemistry uses Fick's law."}},{"data":{"id":"rel_ent_foundation_electrochemistry_uses_ent_butler_volmer_equation","source":"ent_foundation_electrochemistry","target":"ent_butler_volmer_equation","type":"uses","description":"Electrochemistry uses Butler-Volmer Equation."}},{"data":{"id":"rel_ent_method_thermal_simulation_mentions_ent_foundation_electrochemistry","source":"ent_method_thermal_simulation","target":"ent_foundation_electrochemistry","type":"mentions","description":"Co-occurrence relationship extracted from the same Wiki chapter section."}}],"center_id":"ent_foundation_electrochemistry"}