{"nodes":[{"data":{"id":"ent_paper_closing_sim_to_real_gap_for_he_2026","name":"Closing Sim-to-Real Gap for Heavy-loaded Humanoid Agile Motion Skills via Differentiable Simulation","type":"paper","domains":["07_ai_models_algorithms"]}},{"data":{"id":"ent_paper_levy_meta_learning_online_dynamics_2025","name":"Meta-Learning Online Dynamics Model Adaptation in Off-Road Autonomous Driving","type":"paper","domains":["07_ai_models_algorithms","08_software_middleware"]}},{"data":{"id":"ent_method_diffusion_policy","name":"Diffusion Policy","type":"method","domains":["07_ai_models_algorithms","09_data_datasets"]}},{"data":{"id":"ent_paper_task_adaptive_design_of_modula_2026","name":"Task-Adaptive Design of Modular Aerial Manipulators Under Airflow Exposure Constraints","type":"paper","domains":["07_ai_models_algorithms","08_software_middleware"]}},{"data":{"id":"ent_paper_an_empirical_evaluation_of_fou_2022","name":"An Empirical Evaluation of Four Off-the-Shelf Proprietary Visual-Inertial Odometry Systems","type":"paper","domains":["07_ai_models_algorithms","08_software_middleware"]}},{"data":{"id":"ent_paper_li_source_seeking_control_of_unic_2021","name":"Source Seeking Control of Unicycle Robots with 3D-printed Flexible Piezoresistive Sensors","type":"paper","domains":["07_ai_models_algorithms","02_components"]}},{"data":{"id":"ent_paper_towards_bridging_the_gap_syste_2025","name":"Towards bridging the gap: Systematic sim-to-real transfer for diverse legged robots","type":"paper","domains":["07_ai_models_algorithms","08_software_middleware"]}},{"data":{"id":"ent_paper_chi_diffusion_policy_visuomotor_po_2023","name":"Diffusion Policy: Visuomotor Policy Learning via Action Diffusion","type":"paper","domains":["07_ai_models_algorithms","11_applications_markets"]}},{"data":{"id":"ent_paper_learning_contact_representatio_2026","name":"Learning Contact Representation for Leg Odometry","type":"paper","domains":["07_ai_models_algorithms","08_software_middleware"]}},{"data":{"id":"ent_process_p10_3_1","name":"System Identification and Parameter Calibration","type":"method","domains":["07_ai_models_algorithms","06_design_engineering"]}},{"data":{"id":"ent_paper_teetaert_a_sliding_window_filter_for_on_2025","name":"A Sliding-Window Filter for Online Continuous-Time Continuum Robot State Estimation","type":"paper","domains":["07_ai_models_algorithms","06_design_engineering","02_components"]}},{"data":{"id":"ent_paper_preprint_dynamic_modeling_gait_2026","name":"[Preprint] Dynamic Modeling, Gait Synthesis, and Control of a Novel Subsurface Bore Propagator","type":"paper","domains":["07_ai_models_algorithms","08_software_middleware"]}},{"data":{"id":"ent_paper_bridging_the_sim_to_real_gap_f_2025","name":"Bridging the Sim-to-Real Gap for Athletic Loco-Manipulation","type":"paper","domains":["07_ai_models_algorithms","08_software_middleware"]}},{"data":{"id":"ent_paper_coral_auv_cfd_oriented_reinfor_2026","name":"CORAL-AUV: CFD Oriented Reinforcement Learning for Autonomous Underwater Vehicles","type":"paper","domains":["07_ai_models_algorithms","08_software_middleware"]}},{"data":{"id":"ent_paper_hossen_care_finding_root_causes_of_co_2023","name":"CARE: Finding Root Causes of Configuration Issues in Highly-Configurable Robots","type":"paper","domains":["07_ai_models_algorithms","08_software_middleware","04_assembly_integration_testing","05_mass_production"]}},{"data":{"id":"ent_paper_zheng_model_based_control_of_planar_2022","name":"Model-Based Control of Planar Piezoelectric Inchworm Soft Robot for Crawling in Constrained Environments","type":"paper","domains":["07_ai_models_algorithms","02_components","06_design_engineering"]}},{"data":{"id":"ent_paper_nuexo_a_wearable_exoskeleton_c_2025","name":"NuExo: A Wearable Exoskeleton Covering all Upper Limb ROM for Outdoor Data Collection and Teleoperation of Humanoid Robots","type":"paper","domains":["07_ai_models_algorithms","08_software_middleware"]}},{"data":{"id":"ent_paper_sampling_based_system_identifi_2025","name":"Sampling-Based System Identification with Active Exploration for Legged Robot Sim2Real Learning","type":"paper","domains":["07_ai_models_algorithms","08_software_middleware"]}},{"data":{"id":"ent_paper_phypush_one_push_is_all_you_ne_2026","name":"PhyPush: One Push is All You Need for Sensorless Physical Property Estimation with Physics-Guided Transformers","type":"paper","domains":["07_ai_models_algorithms","08_software_middleware"]}},{"data":{"id":"ent_paper_physically_grounded_3d_generat_2026","name":"Physically Grounded 3D Generative Reconstruction under Hand Occlusion using Proprioception and Multi-Contact Touch","type":"paper","domains":["07_ai_models_algorithms","08_software_middleware"]}},{"data":{"id":"ent_paper_chen_adaptive_robotic_information_g_2023","name":"Adaptive Robotic Information Gathering via Non-Stationary Gaussian Processes","type":"paper","domains":["07_ai_models_algorithms"]}},{"data":{"id":"ent_method_sim_to_real","name":"Sim-to-Real Transfer","type":"method","domains":["07_ai_models_algorithms"]}},{"data":{"id":"ent_paper_tendon_actuated_robots_with_a_2026","name":"Tendon-Actuated Robots with a Tapered, Flexible Polymer Backbone: Design, Fabrication, and Modeling","type":"paper","domains":["07_ai_models_algorithms","08_software_middleware"]}},{"data":{"id":"ent_paper_learning_aerodynamics_for_the_2025","name":"Learning Aerodynamics for the Control of Flying Humanoid Robots","type":"paper","domains":["07_ai_models_algorithms"]}},{"data":{"id":"ent_paper_3d_cal_an_open_source_software_2026","name":"3D Cal: An Open-Source Software Library for Depth Reconstruction on Vision-Based Tactile Sensors","type":"paper","domains":["07_ai_models_algorithms","08_software_middleware"]}},{"data":{"id":"ent_foundation_probability_theory","name":"Probability Theory","type":"foundation","domains":["00_foundations"]}},{"data":{"id":"ent_paper_unified_structural_hydrodynami_2026","name":"Unified Structural-Hydrodynamic Modeling of Underwater Underactuated Mechanisms and Soft Robots","type":"paper","domains":["07_ai_models_algorithms","08_software_middleware"]}},{"data":{"id":"ent_paper_petit_bayesian_optimization_for_deve_2020","name":"Bayesian Optimization for Developmental Robotics with Meta-Learning by Parameters Bounds Reduction","type":"paper","domains":["07_ai_models_algorithms","08_software_middleware","03_manufacturing_processes"]}},{"data":{"id":"ent_method_action_token_prediction","name":"Action Token Prediction","type":"method","domains":["07_ai_models_algorithms"]}},{"data":{"id":"ent_paper_a_hybrid_autoencoder_for_robus_2026","name":"A Hybrid Autoencoder for Robust Heightmap Generation from Fused Lidar and Depth Data for Humanoid Robot Locomotion","type":"paper","domains":["07_ai_models_algorithms"]}},{"data":{"id":"ent_paper_jorgensen_thermal_recovery_of_multi_limb_2019","name":"Thermal Recovery of Multi-Limbed Robots with Electric Actuators","type":"paper","domains":["07_ai_models_algorithms","02_components","06_design_engineering"]}},{"data":{"id":"ent_paper_rma_rapid_motor_adaptation_for_2026","name":"RMA: Rapid Motor Adaptation for Legged Robots","type":"paper","domains":["07_ai_models_algorithms","08_software_middleware"]}},{"data":{"id":"ent_paper_impedance_guided_programmable_2026","name":"Impedance-Guided Programmable Transmission of Localized Deformation in Modular Soft Metamaterials","type":"paper","domains":["07_ai_models_algorithms","08_software_middleware"]}},{"data":{"id":"ent_paper_inekformer_a_hybrid_state_esti_2025","name":"InEKFormer: A Hybrid State Estimator for Humanoid Robots","type":"paper","domains":["07_ai_models_algorithms","08_software_middleware"]}},{"data":{"id":"ent_paper_float_drone_for_physical_inter_2026","name":"FLOAT Drone for Physical Interaction: Lateral Airflow Reduction, Wrench Modeling, and Adaptive Control","type":"paper","domains":["07_ai_models_algorithms","08_software_middleware"]}},{"data":{"id":"ent_paper_vins_fusion_an_optimization_ba_2026","name":"VINS-Fusion: An optimization-based multi-sensor state estimator","type":"paper","domains":["07_ai_models_algorithms","08_software_middleware"]}},{"data":{"id":"ent_method_system_identification","name":"System Identification","type":"method","domains":["07_ai_models_algorithms","09_data_datasets"]}},{"data":{"id":"ent_paper_suzuki_attitude_estimation_free_gnss_2023","name":"Attitude-Estimation-Free GNSS and IMU Integration","type":"paper","domains":["07_ai_models_algorithms","02_components","11_applications_markets"]}},{"data":{"id":"ent_paper_oehler_accurate_pose_prediction_on_si_2023","name":"Accurate Pose Prediction on Signed Distance Fields for Mobile Ground Robots in Rough Terrain","type":"paper","domains":["07_ai_models_algorithms","08_software_middleware"]}},{"data":{"id":"ent_paper_adaptive_invariant_extended_ka_2026","name":"Adaptive Invariant Extended Kalman Filter for Legged Robot State Estimation","type":"paper","domains":["07_ai_models_algorithms","08_software_middleware"]}},{"data":{"id":"ent_method_domain_adaptation","name":"Domain Adaptation","type":"method","domains":["07_ai_models_algorithms","09_data_datasets"]}},{"data":{"id":"ent_foundation_linear_algebra","name":"Linear Algebra","type":"foundation","domains":["00_foundations"]}},{"data":{"id":"ent_method_action_chunking_transformer","name":"Action Chunking with Transformers (ACT)","type":"method","domains":["07_ai_models_algorithms","09_data_datasets"]}},{"data":{"id":"ent_paper_learning_to_balance_motor_ther_2026","name":"Learning to Balance Motor Thermal Safety and Quadrupedal Locomotion Performance with Residual Policy","type":"paper","domains":["07_ai_models_algorithms","08_software_middleware"]}},{"data":{"id":"ent_method_hardware_in_the_loop","name":"Hardware-in-the-Loop (HIL)","type":"method","domains":["04_assembly_integration_testing"]}},{"data":{"id":"ent_paper_lee_attention_based_neural_augment_2026","name":"Attention-Based Neural-Augmented Kalman Filter for Legged Robot State Estimation","type":"paper","domains":["07_ai_models_algorithms"]}},{"data":{"id":"ent_paper_action_chunking_with_transform_2023","name":"Action Chunking with Transformers","type":"method","domains":["07_ai_models_algorithms"]}}],"edges":[{"data":{"id":"rel_ent_paper_rma_rapid_motor_adaptation_for_2026_discusses_ent_method_system_identification","source":"ent_paper_rma_rapid_motor_adaptation_for_2026","target":"ent_method_system_identification","type":"discusses","description":"RMA: Rapid Motor Adaptation for Legged Robots discusses System Identification."}},{"data":{"id":"rel_ent_paper_impedance_guided_programmable_2026_discusses_ent_method_system_identification","source":"ent_paper_impedance_guided_programmable_2026","target":"ent_method_system_identification","type":"discusses","description":"Impedance-Guided Programmable Transmission of Localized Deformation in Modular Soft Metamaterials discusses System Identification."}},{"data":{"id":"rel_ent_paper_lee_attention_based_neural_augment_2026_uses_ent_method_system_identification","source":"ent_paper_lee_attention_based_neural_augment_2026","target":"ent_method_system_identification","type":"uses","description":"Attention-Based Neural-Augmented Kalman Filter for Legged Robot State Estimation uses System Identification."}},{"data":{"id":"rel_ent_paper_task_adaptive_design_of_modula_2026_uses_ent_method_system_identification","source":"ent_paper_task_adaptive_design_of_modula_2026","target":"ent_method_system_identification","type":"uses","description":"Task-Adaptive Design of Modular Aerial Manipulators Under Airflow Exposure Constraints uses System Identification."}},{"data":{"id":"rel_ent_paper_jorgensen_thermal_recovery_of_multi_limb_2019_uses_ent_method_system_identification","source":"ent_paper_jorgensen_thermal_recovery_of_multi_limb_2019","target":"ent_method_system_identification","type":"uses","description":"Thermal Recovery of Multi-Limbed Robots with Electric Actuators uses System Identification."}},{"data":{"id":"rel_ent_method_system_identification_has_prerequisite_ent_foundation_probability_theory","source":"ent_method_system_identification","target":"ent_foundation_probability_theory","type":"has_prerequisite","description":"System Identification has prerequisite Probability Theory."}},{"data":{"id":"rel_ent_paper_nuexo_a_wearable_exoskeleton_c_2025_discusses_ent_method_system_identification","source":"ent_paper_nuexo_a_wearable_exoskeleton_c_2025","target":"ent_method_system_identification","type":"discusses","description":"NuExo: A Wearable Exoskeleton Covering all Upper Limb ROM for Outdoor Data Collection and Teleoperation of Humanoid Robots discusses System Identification."}},{"data":{"id":"rel_ent_paper_closing_sim_to_real_gap_for_he_2026_uses_ent_method_system_identification","source":"ent_paper_closing_sim_to_real_gap_for_he_2026","target":"ent_method_system_identification","type":"uses","description":"Closing Sim-to-Real Gap for Heavy-loaded Humanoid Agile Motion Skills via Differentiable Simulation uses System Identification."}},{"data":{"id":"rel_ent_process_p10_3_1_has_prerequisite_ent_method_system_identification","source":"ent_process_p10_3_1","target":"ent_method_system_identification","type":"has_prerequisite","description":"System Identification and Parameter Calibration has prerequisite System Identification."}},{"data":{"id":"rel_ent_paper_adaptive_invariant_extended_ka_2026_uses_ent_method_system_identification","source":"ent_paper_adaptive_invariant_extended_ka_2026","target":"ent_method_system_identification","type":"uses","description":"Adaptive Invariant Extended Kalman Filter for Legged Robot State Estimation uses System Identification."}},{"data":{"id":"rel_ent_paper_physically_grounded_3d_generat_2026_uses_ent_method_system_identification","source":"ent_paper_physically_grounded_3d_generat_2026","target":"ent_method_system_identification","type":"uses","description":"Physically Grounded 3D Generative Reconstruction under Hand Occlusion using Proprioception and Multi-Contact Touch uses System Identification."}},{"data":{"id":"rel_ent_paper_a_hybrid_autoencoder_for_robus_2026_uses_ent_method_system_identification","source":"ent_paper_a_hybrid_autoencoder_for_robus_2026","target":"ent_method_system_identification","type":"uses","description":"A Hybrid Autoencoder for Robust Heightmap Generation from Fused Lidar and Depth Data for Humanoid Robot Locomotion uses System Identification."}},{"data":{"id":"rel_ent_paper_towards_bridging_the_gap_syste_2025_uses_ent_method_system_identification","source":"ent_paper_towards_bridging_the_gap_syste_2025","target":"ent_method_system_identification","type":"uses","description":"Towards bridging the gap: Systematic sim-to-real transfer for diverse legged robots uses System Identification."}},{"data":{"id":"rel_ent_paper_float_drone_for_physical_inter_2026_uses_ent_method_system_identification","source":"ent_paper_float_drone_for_physical_inter_2026","target":"ent_method_system_identification","type":"uses","description":"FLOAT Drone for Physical Interaction: Lateral Airflow Reduction, Wrench Modeling, and Adaptive Control uses System Identification."}},{"data":{"id":"rel_ent_paper_learning_to_balance_motor_ther_2026_uses_ent_method_system_identification","source":"ent_paper_learning_to_balance_motor_ther_2026","target":"ent_method_system_identification","type":"uses","description":"Learning to Balance Motor Thermal Safety and Quadrupedal Locomotion Performance with Residual Policy uses System Identification."}},{"data":{"id":"rel_ent_paper_tendon_actuated_robots_with_a_2026_uses_ent_method_system_identification","source":"ent_paper_tendon_actuated_robots_with_a_2026","target":"ent_method_system_identification","type":"uses","description":"Tendon-Actuated Robots with a Tapered, Flexible Polymer Backbone: Design, Fabrication, and Modeling uses System Identification."}},{"data":{"id":"rel_ent_paper_teetaert_a_sliding_window_filter_for_on_2025_uses_ent_method_system_identification","source":"ent_paper_teetaert_a_sliding_window_filter_for_on_2025","target":"ent_method_system_identification","type":"uses","description":"A Sliding-Window Filter for Online Continuous-Time Continuum Robot State Estimation uses System Identification."}},{"data":{"id":"rel_ent_paper_li_source_seeking_control_of_unic_2021_uses_ent_method_system_identification","source":"ent_paper_li_source_seeking_control_of_unic_2021","target":"ent_method_system_identification","type":"uses","description":"Source Seeking Control of Unicycle Robots with 3D-printed Flexible Piezoresistive Sensors uses System Identification."}},{"data":{"id":"rel_ent_paper_oehler_accurate_pose_prediction_on_si_2023_uses_ent_method_system_identification","source":"ent_paper_oehler_accurate_pose_prediction_on_si_2023","target":"ent_method_system_identification","type":"uses","description":"Accurate Pose Prediction on Signed Distance Fields for Mobile Ground Robots in Rough Terrain uses System Identification."}},{"data":{"id":"rel_ent_paper_chen_adaptive_robotic_information_g_2023_discusses_ent_method_system_identification","source":"ent_paper_chen_adaptive_robotic_information_g_2023","target":"ent_method_system_identification","type":"discusses","description":"Adaptive Robotic Information Gathering via Non-Stationary Gaussian Processes discusses System Identification."}},{"data":{"id":"rel_ent_paper_preprint_dynamic_modeling_gait_2026_discusses_ent_method_system_identification","source":"ent_paper_preprint_dynamic_modeling_gait_2026","target":"ent_method_system_identification","type":"discusses","description":"[Preprint] Dynamic Modeling, Gait Synthesis, and Control of a Novel Subsurface Bore Propagator discusses System Identification."}},{"data":{"id":"rel_ent_paper_hossen_care_finding_root_causes_of_co_2023_uses_ent_method_system_identification","source":"ent_paper_hossen_care_finding_root_causes_of_co_2023","target":"ent_method_system_identification","type":"uses","description":"CARE: Finding Root Causes of Configuration Issues in Highly-Configurable Robots uses System Identification."}},{"data":{"id":"rel_ent_paper_an_empirical_evaluation_of_fou_2022_mentions_ent_method_system_identification","source":"ent_paper_an_empirical_evaluation_of_fou_2022","target":"ent_method_system_identification","type":"mentions","description":"An Empirical Evaluation of Four Off-the-Shelf Proprietary Visual-Inertial Odometry Systems mentions System Identification."}},{"data":{"id":"rel_ent_method_domain_adaptation_mentions_ent_method_system_identification","source":"ent_method_domain_adaptation","target":"ent_method_system_identification","type":"mentions","description":"Domain Adaptation mentions System Identification."}},{"data":{"id":"rel_ent_paper_levy_meta_learning_online_dynamics_2025_uses_ent_method_system_identification","source":"ent_paper_levy_meta_learning_online_dynamics_2025","target":"ent_method_system_identification","type":"uses","description":"Meta-Learning Online Dynamics Model Adaptation in Off-Road Autonomous Driving uses System Identification."}},{"data":{"id":"rel_ent_paper_phypush_one_push_is_all_you_ne_2026_uses_ent_method_system_identification","source":"ent_paper_phypush_one_push_is_all_you_ne_2026","target":"ent_method_system_identification","type":"uses","description":"PhyPush: One Push is All You Need for Sensorless Physical Property Estimation with Physics-Guided Transformers uses System Identification."}},{"data":{"id":"rel_ent_method_hardware_in_the_loop_has_prerequisite_ent_method_system_identification","source":"ent_method_hardware_in_the_loop","target":"ent_method_system_identification","type":"has_prerequisite","description":"Hardware-in-the-Loop (HIL) has prerequisite System Identification."}},{"data":{"id":"rel_ent_paper_3d_cal_an_open_source_software_2026_uses_ent_method_system_identification","source":"ent_paper_3d_cal_an_open_source_software_2026","target":"ent_method_system_identification","type":"uses","description":"3D Cal: An Open-Source Software Library for Depth Reconstruction on Vision-Based Tactile Sensors uses System Identification."}},{"data":{"id":"rel_ent_method_sim_to_real_has_prerequisite_ent_method_system_identification","source":"ent_method_sim_to_real","target":"ent_method_system_identification","type":"has_prerequisite","description":"Sim-to-Real Transfer has prerequisite System Identification."}},{"data":{"id":"rel_ent_paper_suzuki_attitude_estimation_free_gnss_2023_discusses_ent_method_system_identification","source":"ent_paper_suzuki_attitude_estimation_free_gnss_2023","target":"ent_method_system_identification","type":"discusses","description":"Attitude-Estimation-Free GNSS and IMU Integration discusses System Identification."}},{"data":{"id":"rel_ent_paper_unified_structural_hydrodynami_2026_discusses_ent_method_system_identification","source":"ent_paper_unified_structural_hydrodynami_2026","target":"ent_method_system_identification","type":"discusses","description":"Unified Structural-Hydrodynamic Modeling of Underwater Underactuated Mechanisms and Soft Robots discusses System Identification."}},{"data":{"id":"rel_ent_paper_zheng_model_based_control_of_planar_2022_uses_ent_method_system_identification","source":"ent_paper_zheng_model_based_control_of_planar_2022","target":"ent_method_system_identification","type":"uses","description":"Model-Based Control of Planar Piezoelectric Inchworm Soft Robot for Crawling in Constrained Environments uses System Identification."}},{"data":{"id":"rel_ent_paper_learning_aerodynamics_for_the_2025_uses_ent_method_system_identification","source":"ent_paper_learning_aerodynamics_for_the_2025","target":"ent_method_system_identification","type":"uses","description":"Learning Aerodynamics for the Control of Flying Humanoid Robots uses System Identification."}},{"data":{"id":"rel_ent_paper_inekformer_a_hybrid_state_esti_2025_uses_ent_method_system_identification","source":"ent_paper_inekformer_a_hybrid_state_esti_2025","target":"ent_method_system_identification","type":"uses","description":"InEKFormer: A Hybrid State Estimator for Humanoid Robots uses System Identification."}},{"data":{"id":"rel_ent_method_system_identification_has_prerequisite_ent_foundation_linear_algebra","source":"ent_method_system_identification","target":"ent_foundation_linear_algebra","type":"has_prerequisite","description":"System Identification has prerequisite Linear Algebra."}},{"data":{"id":"rel_ent_paper_coral_auv_cfd_oriented_reinfor_2026_discusses_ent_method_system_identification","source":"ent_paper_coral_auv_cfd_oriented_reinfor_2026","target":"ent_method_system_identification","type":"discusses","description":"CORAL-AUV: CFD Oriented Reinforcement Learning for Autonomous Underwater Vehicles discusses System Identification."}},{"data":{"id":"rel_ent_paper_petit_bayesian_optimization_for_deve_2020_discusses_ent_method_system_identification","source":"ent_paper_petit_bayesian_optimization_for_deve_2020","target":"ent_method_system_identification","type":"discusses","description":"Bayesian Optimization for Developmental Robotics with Meta-Learning by Parameters Bounds Reduction discusses System Identification."}},{"data":{"id":"rel_ent_paper_bridging_the_sim_to_real_gap_f_2025_uses_ent_method_system_identification","source":"ent_paper_bridging_the_sim_to_real_gap_f_2025","target":"ent_method_system_identification","type":"uses","description":"Bridging the Sim-to-Real Gap for Athletic Loco-Manipulation uses System Identification."}},{"data":{"id":"rel_ent_paper_vins_fusion_an_optimization_ba_2026_uses_ent_method_system_identification","source":"ent_paper_vins_fusion_an_optimization_ba_2026","target":"ent_method_system_identification","type":"uses","description":"VINS-Fusion: An optimization-based multi-sensor state estimator uses System Identification."}},{"data":{"id":"rel_ent_paper_sampling_based_system_identifi_2025_mentions_ent_method_system_identification","source":"ent_paper_sampling_based_system_identifi_2025","target":"ent_method_system_identification","type":"mentions","description":"Sampling-Based System Identification with Active Exploration for Legged Robot Sim2Real Learning mentions System Identification."}},{"data":{"id":"rel_ent_paper_learning_contact_representatio_2026_uses_ent_method_system_identification","source":"ent_paper_learning_contact_representatio_2026","target":"ent_method_system_identification","type":"uses","description":"Learning Contact Representation for Leg Odometry uses System Identification."}},{"data":{"id":"rel_ent_paper_action_chunking_with_transform_2023_deployed_on_ent_method_system_identification","source":"ent_paper_action_chunking_with_transform_2023","target":"ent_method_system_identification","type":"implemented_on","description":"Cross-layer link extracted from Wiki chapter 18. "}},{"data":{"id":"rel_ent_method_action_token_prediction_deployed_on_ent_method_system_identification","source":"ent_method_action_token_prediction","target":"ent_method_system_identification","type":"instantiates","description":"Cross-layer link extracted from Wiki chapter 18. "}},{"data":{"id":"rel_ent_method_action_chunking_transformer_deployed_on_ent_method_system_identification","source":"ent_method_action_chunking_transformer","target":"ent_method_system_identification","type":"implemented_on","description":"Cross-layer link extracted from Wiki chapter 18. "}},{"data":{"id":"rel_ent_paper_chi_diffusion_policy_visuomotor_po_2023_deployed_on_ent_method_system_identification","source":"ent_paper_chi_diffusion_policy_visuomotor_po_2023","target":"ent_method_system_identification","type":"implemented_on","description":"Cross-layer link extracted from Wiki chapter 18. "}},{"data":{"id":"rel_ent_method_diffusion_policy_deployed_on_ent_method_system_identification","source":"ent_method_diffusion_policy","target":"ent_method_system_identification","type":"implemented_on","description":"Cross-layer link extracted from Wiki chapter 18. "}}],"center_id":"ent_method_system_identification"}