{"nodes":[{"data":{"id":"ent_method_whole_body_control","name":"Whole-Body Control (WBC)","type":"method","domains":["07_ai_models_algorithms"]}},{"data":{"id":"ent_paper_a_survey_of_behavior_foundatio_2025","name":"A Survey of Behavior Foundation Model: Next-Generation Whole-Body Control System of Humanoid Robots","type":"paper","domains":["07_ai_models_algorithms","08_software_middleware"]}}],"edges":[{"data":{"id":"rel_ent_paper_a_survey_of_behavior_foundatio_2025_mentions_ent_method_whole_body_control","source":"ent_paper_a_survey_of_behavior_foundatio_2025","target":"ent_method_whole_body_control","type":"mentions","description":"A Survey of Behavior Foundation Model: Next-Generation Whole-Body Control System of Humanoid Robots mentions Whole-Body Control (WBC)."}}],"center_id":"ent_paper_a_survey_of_behavior_foundatio_2025"}