{"nodes":[{"data":{"id":"ent_method_hierarchical_qp_wbc","name":"Hierarchical QP Whole-Body Control","type":"method","domains":["07_ai_models_algorithms","06_design_engineering"]}},{"data":{"id":"ent_method_whole_body_control","name":"Whole-Body Control (WBC)","type":"method","domains":["07_ai_models_algorithms"]}},{"data":{"id":"ent_method_gait_planning","name":"Gait Planning","type":"method","domains":["07_ai_models_algorithms"]}},{"data":{"id":"ent_paper_vmp_versatile_motion_priors_fo_2024","name":"VMP: Versatile Motion Priors for Robustly Tracking Motion on Physical Characters","type":"paper","domains":["07_ai_models_algorithms","08_software_middleware"]}}],"edges":[{"data":{"id":"rel_ent_paper_vmp_versatile_motion_priors_fo_2024_uses_ent_method_hierarchical_qp_wbc","source":"ent_paper_vmp_versatile_motion_priors_fo_2024","target":"ent_method_hierarchical_qp_wbc","type":"uses","description":"VMP: Versatile Motion Priors for Robustly Tracking Motion on Physical Characters uses Hierarchical QP Whole-Body Control."}},{"data":{"id":"rel_ent_paper_vmp_versatile_motion_priors_fo_2024_studies_ent_method_whole_body_control","source":"ent_paper_vmp_versatile_motion_priors_fo_2024","target":"ent_method_whole_body_control","type":"studies","description":"VMP: Versatile Motion Priors for Robustly Tracking Motion on Physical Characters studies Whole-Body Control (WBC)."}},{"data":{"id":"rel_ent_paper_vmp_versatile_motion_priors_fo_2024_discusses_ent_method_gait_planning","source":"ent_paper_vmp_versatile_motion_priors_fo_2024","target":"ent_method_gait_planning","type":"discusses","description":"VMP: Versatile Motion Priors for Robustly Tracking Motion on Physical Characters discusses Gait Planning."}}],"center_id":"ent_paper_vmp_versatile_motion_priors_fo_2024"}