{"nodes":[{"data":{"id":"ent_concept_world_model","name":"世界模型","type":"concept","domains":["07_ai_models_algorithms"]}},{"data":{"id":"ent_paper_kimera_an_open_source_library_2026","name":"Kimera: an Open-Source Library for Real-Time Metric-Semantic Localization and Mapping","type":"paper","domains":["07_ai_models_algorithms","08_software_middleware"]}},{"data":{"id":"ent_method_whole_body_control","name":"全身控制（WBC）","type":"method","domains":["07_ai_models_algorithms"]}},{"data":{"id":"ent_process_p12_1_2","name":"SLAM 与场景理解","type":"method","domains":["07_ai_models_algorithms"]}}],"edges":[{"data":{"id":"rel_ent_paper_kimera_an_open_source_library_2026_mentions_ent_process_p12_1_2","source":"ent_paper_kimera_an_open_source_library_2026","target":"ent_process_p12_1_2","type":"mentions","description":"Kimera: an Open-Source Library for Real-Time Metric-Semantic Localization and Mapping提及SLAM 与场景理解。"}},{"data":{"id":"rel_ent_paper_kimera_an_open_source_library_2026_discusses_ent_concept_world_model","source":"ent_paper_kimera_an_open_source_library_2026","target":"ent_concept_world_model","type":"discusses","description":"Kimera: an Open-Source Library for Real-Time Metric-Semantic Localization and Mappingdiscusses世界模型。"}},{"data":{"id":"rel_ent_paper_kimera_an_open_source_library_2026_proposes_ent_method_whole_body_control","source":"ent_paper_kimera_an_open_source_library_2026","target":"ent_method_whole_body_control","type":"proposes","description":"Kimera: an Open-Source Library for Real-Time Metric-Semantic Localization and Mapping提出全身控制（WBC）。"}}],"center_id":"ent_paper_kimera_an_open_source_library_2026"}