{"nodes":[{"data":{"id":"ent_method_fleet_data_flywheel","name":"车队数据飞轮","type":"method","domains":["09_data_datasets"]}},{"data":{"id":"ent_concept_data_flywheel","name":"数据飞轮","type":"concept","domains":["11_applications_markets","12_policy_regulation_ethics"]}},{"data":{"id":"ent_technology_ota_software_update_2024","name":"OTA 软件更新","type":"technology","domains":["08_software_middleware","05_mass_production"]}}],"edges":[{"data":{"id":"rel_ent_concept_data_flywheel_mentions_ent_method_fleet_data_flywheel","source":"ent_concept_data_flywheel","target":"ent_method_fleet_data_flywheel","type":"mentions","description":"数据飞轮提及车队数据飞轮。"}},{"data":{"id":"rel_ent_method_fleet_data_flywheel_mentions_ent_technology_ota_software_update_2024","source":"ent_method_fleet_data_flywheel","target":"ent_technology_ota_software_update_2024","type":"mentions","description":"车队数据飞轮提及OTA 软件更新。"}}],"center_id":"ent_method_fleet_data_flywheel"}