{"nodes":[{"data":{"id":"ent_material_sic_gan_power_devices","name":"SiC/GaN功率器件材料","type":"material","domains":["01_raw_materials"]}},{"data":{"id":"ent_component_battery_management_system","name":"电池管理系统","type":"component","domains":["02_components","06_design_engineering","04_assembly_integration_testing"]}},{"data":{"id":"ent_tech_li_battery_humanoid","name":"人形机器人锂离子电池系统","type":"technology","domains":["01_raw_materials","02_components","03_manufacturing_processes"]}},{"data":{"id":"ent_robot_system_unitree_g1","name":"Unitree G1 人形机器人","type":"robot_system","domains":["02_components","06_design_engineering","05_mass_production","11_applications_markets"]}},{"data":{"id":"ent_material_rare_earth_supply","name":"稀土元素供应链","type":"material","domains":["01_raw_materials"]}},{"data":{"id":"ent_component_main_board_power_sensor","name":"主板功率传感器","type":"component","domains":["02_components","06_design_engineering","10_evaluation_benchmarks"]}},{"data":{"id":"ent_robot_system_tesla_optimus","name":"Tesla Optimus","type":"robot_system","domains":["05_mass_production","06_design_engineering","11_applications_markets"]}},{"data":{"id":"ent_method_equivalent_circuit_battery_model","name":"等效电路电池模型","type":"method","domains":["02_components","06_design_engineering","00_foundations"]}}],"edges":[{"data":{"id":"rel_ent_tech_li_battery_humanoid_integrates_ent_component_battery_management_system","source":"ent_tech_li_battery_humanoid","target":"ent_component_battery_management_system","type":"integrates","description":"ent_tech_li_battery_humanoid 集成 ent_component_battery_management_system 以实现监测、保护和电池均衡。"}},{"data":{"id":"rel_ent_tech_li_battery_humanoid_enables_ent_component_main_board_power_sensor","source":"ent_tech_li_battery_humanoid","target":"ent_component_main_board_power_sensor","type":"enables","description":"Main-Board Power Sensor enables or supports Lithium-Ion Battery System for Humanoid Robots."}},{"data":{"id":"rel_ent_tech_li_battery_humanoid_enables_ent_robot_system_tesla_optimus","source":"ent_tech_li_battery_humanoid","target":"ent_robot_system_tesla_optimus","type":"enables","description":"特斯拉 Optimus 依靠机载锂离子电池组实现移动和驱动；2.3 kWh 电池组支持约两小时的动态运行时间。"}},{"data":{"id":"rel_ent_material_sic_gan_power_devices_mentions_ent_tech_li_battery_humanoid","source":"ent_material_sic_gan_power_devices","target":"ent_tech_li_battery_humanoid","type":"mentions","description":"SiC/GaN功率器件材料提及人形机器人锂离子电池系统。"}},{"data":{"id":"rel_ent_material_rare_earth_supply_mentions_ent_tech_li_battery_humanoid","source":"ent_material_rare_earth_supply","target":"ent_tech_li_battery_humanoid","type":"mentions","description":"稀土元素供应链提及人形机器人锂离子电池系统。"}},{"data":{"id":"rel_ent_tech_li_battery_humanoid_requires_ent_component_battery_management_system","source":"ent_tech_li_battery_humanoid","target":"ent_component_battery_management_system","type":"requires","description":"人形机器人用锂离子电池组需要电池管理系统来维持电芯健康、优化性能并防止故障状态。"}},{"data":{"id":"rel_ent_tech_li_battery_humanoid_enables_ent_robot_system_unitree_g1","source":"ent_tech_li_battery_humanoid","target":"ent_robot_system_unitree_g1","type":"enables","description":"宇树 G1 使用机载 864 Wh 电池组为其关节和运动供电。"}},{"data":{"id":"rel_ent_tech_li_battery_humanoid_uses_ent_method_equivalent_circuit_battery_model","source":"ent_tech_li_battery_humanoid","target":"ent_method_equivalent_circuit_battery_model","type":"uses","description":"ent_tech_li_battery_humanoid 使用 ent_method_equivalent_circuit_battery_model 进行状态估计和电压预测。"}}],"center_id":"ent_tech_li_battery_humanoid"}