{"nodes":[{"data":{"id":"ent_algorithm_ppo","name":"近端策略优化（PPO）","type":"algorithm","domains":["07_ai_models_algorithms"]}},{"data":{"id":"ent_method_domain_randomization","name":"域随机化","type":"method","domains":["07_ai_models_algorithms","09_data_datasets"]}},{"data":{"id":"ent_method_whole_body_control","name":"全身控制（WBC）","type":"method","domains":["07_ai_models_algorithms"]}},{"data":{"id":"ent_paper_lips_large_scale_humanoid_robo_2025","name":"LiPS: Large-Scale Humanoid Robot RL with Parallel-Series Structures","type":"paper","domains":["07_ai_models_algorithms"]}}],"edges":[{"data":{"id":"rel_ent_paper_lips_large_scale_humanoid_robo_2025_uses_ent_algorithm_ppo","source":"ent_paper_lips_large_scale_humanoid_robo_2025","target":"ent_algorithm_ppo","type":"uses","description":"LiPS: Large-Scale Humanoid Robot RL with Parallel-Series Structures使用近端策略优化（PPO）。"}},{"data":{"id":"rel_ent_paper_lips_large_scale_humanoid_robo_2025_uses_ent_method_domain_randomization","source":"ent_paper_lips_large_scale_humanoid_robo_2025","target":"ent_method_domain_randomization","type":"uses","description":"LiPS: Large-Scale Humanoid Robot RL with Parallel-Series Structures使用域随机化。"}},{"data":{"id":"rel_ent_paper_lips_large_scale_humanoid_robo_2025_discusses_ent_method_whole_body_control","source":"ent_paper_lips_large_scale_humanoid_robo_2025","target":"ent_method_whole_body_control","type":"discusses","description":"LiPS: Large-Scale Humanoid Robot RL with Parallel-Series Structuresdiscusses全身控制（WBC）。"}}],"center_id":"ent_paper_lips_large_scale_humanoid_robo_2025"}