{"nodes":[{"data":{"id":"ent_method_model_predictive_control","name":"模型预测控制（MPC）","type":"method","domains":["07_ai_models_algorithms"]}},{"data":{"id":"ent_paper_embedding_classical_balance_co_2026","name":"Embedding Classical Balance Control Principles in Reinforcement Learning for Humanoid Recovery","type":"paper","domains":["07_ai_models_algorithms","08_software_middleware"]}},{"data":{"id":"ent_paper_stability_aware_retargeting_fo_2025","name":"Stability-Aware Retargeting for Humanoid Multi-Contact Teleoperation","type":"paper","domains":["07_ai_models_algorithms","08_software_middleware"]}},{"data":{"id":"ent_method_forward_kinematics","name":"正运动学","type":"method","domains":["06_design_engineering"]}},{"data":{"id":"ent_process_p10_2_1","name":"站立与抗扰平衡控制","type":"method","domains":["07_ai_models_algorithms","06_design_engineering"]}},{"data":{"id":"ent_method_hierarchical_qp_wbc","name":"分层二次规划全身控制","type":"method","domains":["07_ai_models_algorithms","06_design_engineering"]}},{"data":{"id":"ent_paper_wiedebach_walking_on_partial_footholds_i_2016","name":"Atlas人形机器人在部分支撑面（包括线接触）上的行走方法","type":"paper","domains":["07_ai_models_algorithms"]}},{"data":{"id":"ent_paper_hover_versatile_humanoid_contr_2024","name":"HOVER 通用人形控制器","type":"method","domains":["07_ai_models_algorithms"]}},{"data":{"id":"ent_paper_architecture_is_all_you_need_d_2025","name":"Architecture Is All You Need: Diversity-Enabled Sweet Spots for Robust Humanoid Locomotion","type":"paper","domains":["07_ai_models_algorithms"]}},{"data":{"id":"ent_principle_capture_point","name":"捕获点","type":"principle","domains":["07_ai_models_algorithms"]}},{"data":{"id":"ent_process_p10","name":"运动控制算法开发与验证（Motion Control）","type":"method","domains":["07_ai_models_algorithms","06_design_engineering"]}},{"data":{"id":"ent_paper_sakurai_bipedal_robot_running_human_li_2024","name":"双足机器人跑步：利用快/慢自适应实现类人驱动时机","type":"paper","domains":["07_ai_models_algorithms","02_components"]}},{"data":{"id":"ent_paper_end_to_end_humanoid_robot_safe_2025","name":"End-to-End Humanoid Robot Safe and Comfortable Locomotion Policy","type":"paper","domains":["07_ai_models_algorithms"]}},{"data":{"id":"ent_paper_whole_body_humanoid_robot_loco_2024","name":"Whole-body Humanoid Robot Locomotion with Human Reference","type":"paper","domains":["07_ai_models_algorithms"]}},{"data":{"id":"ent_formalism_floating_base_dynamics","name":"浮动基动力学","type":"formalism","domains":["06_design_engineering"]}},{"data":{"id":"ent_paper_unified_humanoid_fall_safety_p_2025","name":"Unified Humanoid Fall-Safety Policy from a Few Demonstrations","type":"paper","domains":["07_ai_models_algorithms","08_software_middleware"]}},{"data":{"id":"ent_paper_ficht_centroidal_state_estimation_an_2023","name":"面向硬件受限人形机器人的质心状态估计与控制","type":"paper","domains":["07_ai_models_algorithms","02_components"]}},{"data":{"id":"ent_method_inverse_kinematics","name":"逆运动学","type":"method","domains":["06_design_engineering"]}},{"data":{"id":"ent_paper_discovering_self_protective_fa_2025","name":"Discovering Self-Protective Falling Policy for Humanoid Robot via Deep Reinforcement Learning","type":"paper","domains":["07_ai_models_algorithms","08_software_middleware"]}},{"data":{"id":"ent_paper_learning_symmetric_and_low_ene_2018","name":"Learning Symmetric and Low-energy Locomotion","type":"paper","domains":["07_ai_models_algorithms"]}},{"data":{"id":"ent_paper_cmr_contractive_mapping_embedd_2026","name":"CMR: Contractive Mapping Embeddings for Robust Humanoid Locomotion on Unstructured Terrains","type":"paper","domains":["07_ai_models_algorithms"]}},{"data":{"id":"ent_paper_chasing_stability_humanoid_run_2025","name":"Chasing Stability: Humanoid Running via Control Lyapunov Function Guided RL","type":"paper","domains":["07_ai_models_algorithms"]}},{"data":{"id":"ent_paper_biomechanical_comparisons_reve_2026","name":"Biomechanical Comparisons Reveal Divergence of Human and Humanoid Gaits","type":"paper","domains":["07_ai_models_algorithms"]}},{"data":{"id":"ent_paper_learning_humanoid_arm_motion_v_2025","name":"Learning Humanoid Arm Motion via Centroidal Momentum Regularized Multi-Agent Reinforcement Learning","type":"paper","domains":["07_ai_models_algorithms"]}},{"data":{"id":"ent_paper_vigor_visual_goal_in_context_i_2026","name":"VIGOR: Visual Goal-In-Context Inference for Unified Humanoid Fall Safety","type":"paper","domains":["07_ai_models_algorithms","08_software_middleware"]}},{"data":{"id":"ent_paper_prasad_geometric_mechanics_of_contact_2023","name":"接触切换系统的几何力学","type":"paper","domains":["07_ai_models_algorithms","06_design_engineering"]}},{"data":{"id":"ent_method_fea_finite_element_analysis","name":"有限元分析（FEA）","type":"method","domains":["06_design_engineering"]}},{"data":{"id":"ent_principle_zero_moment_point","name":"零力矩点（ZMP）","type":"principle","domains":["06_design_engineering","07_ai_models_algorithms"]}},{"data":{"id":"ent_paper_shield_safety_on_humanoids_via_2025","name":"SHIELD: Safety on Humanoids via CBFs In Expectation on Learned Dynamics","type":"paper","domains":["07_ai_models_algorithms"]}},{"data":{"id":"ent_method_gait_planning","name":"步态规划","type":"method","domains":["07_ai_models_algorithms"]}}],"edges":[{"data":{"id":"rel_ent_method_hierarchical_qp_wbc_mentions_ent_principle_capture_point","source":"ent_method_hierarchical_qp_wbc","target":"ent_principle_capture_point","type":"mentions","description":"分层二次规划全身控制提及捕获点。"}},{"data":{"id":"rel_ent_paper_wiedebach_walking_on_partial_footholds_i_2016_uses_ent_principle_capture_point","source":"ent_paper_wiedebach_walking_on_partial_footholds_i_2016","target":"ent_principle_capture_point","type":"uses","description":"Atlas人形机器人在部分支撑面（包括线接触）上的行走方法使用捕获点。"}},{"data":{"id":"rel_ent_paper_stability_aware_retargeting_fo_2025_uses_ent_principle_capture_point","source":"ent_paper_stability_aware_retargeting_fo_2025","target":"ent_principle_capture_point","type":"uses","description":"Stability-Aware Retargeting for Humanoid Multi-Contact Teleoperation使用捕获点。"}},{"data":{"id":"rel_ent_paper_prasad_geometric_mechanics_of_contact_2023_discusses_ent_principle_capture_point","source":"ent_paper_prasad_geometric_mechanics_of_contact_2023","target":"ent_principle_capture_point","type":"discusses","description":"接触切换系统的几何力学discusses捕获点。"}},{"data":{"id":"rel_ent_paper_unified_humanoid_fall_safety_p_2025_discusses_ent_principle_capture_point","source":"ent_paper_unified_humanoid_fall_safety_p_2025","target":"ent_principle_capture_point","type":"discusses","description":"Unified Humanoid Fall-Safety Policy from a Few Demonstrationsdiscusses捕获点。"}},{"data":{"id":"rel_ent_paper_whole_body_humanoid_robot_loco_2024_uses_ent_principle_capture_point","source":"ent_paper_whole_body_humanoid_robot_loco_2024","target":"ent_principle_capture_point","type":"uses","description":"Whole-body Humanoid Robot Locomotion with Human Reference使用捕获点。"}},{"data":{"id":"rel_ent_process_p10_uses_ent_principle_capture_point","source":"ent_process_p10","target":"ent_principle_capture_point","type":"uses","description":"运动控制算法开发与验证（Motion Control）使用捕获点。"}},{"data":{"id":"rel_ent_paper_hover_versatile_humanoid_contr_2024_mentions_ent_principle_capture_point","source":"ent_paper_hover_versatile_humanoid_contr_2024","target":"ent_principle_capture_point","type":"mentions","description":"HOVER 通用人形控制器提及捕获点。"}},{"data":{"id":"rel_ent_paper_discovering_self_protective_fa_2025_discusses_ent_principle_capture_point","source":"ent_paper_discovering_self_protective_fa_2025","target":"ent_principle_capture_point","type":"discusses","description":"Discovering Self-Protective Falling Policy for Humanoid Robot via Deep Reinforcement Learningdiscusses捕获点。"}},{"data":{"id":"rel_ent_paper_cmr_contractive_mapping_embedd_2026_uses_ent_principle_capture_point","source":"ent_paper_cmr_contractive_mapping_embedd_2026","target":"ent_principle_capture_point","type":"uses","description":"CMR: Contractive Mapping Embeddings for Robust Humanoid Locomotion on Unstructured Terrains使用捕获点。"}},{"data":{"id":"rel_ent_paper_embedding_classical_balance_co_2026_uses_ent_principle_capture_point","source":"ent_paper_embedding_classical_balance_co_2026","target":"ent_principle_capture_point","type":"uses","description":"Embedding Classical Balance Control Principles in Reinforcement Learning for Humanoid Recovery使用捕获点。"}},{"data":{"id":"rel_ent_paper_chasing_stability_humanoid_run_2025_discusses_ent_principle_capture_point","source":"ent_paper_chasing_stability_humanoid_run_2025","target":"ent_principle_capture_point","type":"discusses","description":"Chasing Stability: Humanoid Running via Control Lyapunov Function Guided RLdiscusses捕获点。"}},{"data":{"id":"rel_ent_paper_sakurai_bipedal_robot_running_human_li_2024_discusses_ent_principle_capture_point","source":"ent_paper_sakurai_bipedal_robot_running_human_li_2024","target":"ent_principle_capture_point","type":"discusses","description":"双足机器人跑步：利用快/慢自适应实现类人驱动时机discusses捕获点。"}},{"data":{"id":"rel_ent_paper_vigor_visual_goal_in_context_i_2026_discusses_ent_principle_capture_point","source":"ent_paper_vigor_visual_goal_in_context_i_2026","target":"ent_principle_capture_point","type":"discusses","description":"VIGOR: Visual Goal-In-Context Inference for Unified Humanoid Fall Safetydiscusses捕获点。"}},{"data":{"id":"rel_ent_process_p10_2_1_uses_ent_principle_capture_point","source":"ent_process_p10_2_1","target":"ent_principle_capture_point","type":"uses","description":"站立与抗扰平衡控制使用捕获点。"}},{"data":{"id":"rel_ent_paper_biomechanical_comparisons_reve_2026_discusses_ent_principle_capture_point","source":"ent_paper_biomechanical_comparisons_reve_2026","target":"ent_principle_capture_point","type":"discusses","description":"Biomechanical Comparisons Reveal Divergence of Human and Humanoid Gaitsdiscusses捕获点。"}},{"data":{"id":"rel_ent_paper_ficht_centroidal_state_estimation_an_2023_uses_ent_principle_capture_point","source":"ent_paper_ficht_centroidal_state_estimation_an_2023","target":"ent_principle_capture_point","type":"uses","description":"面向硬件受限人形机器人的质心状态估计与控制使用捕获点。"}},{"data":{"id":"rel_ent_paper_learning_symmetric_and_low_ene_2018_discusses_ent_principle_capture_point","source":"ent_paper_learning_symmetric_and_low_ene_2018","target":"ent_principle_capture_point","type":"discusses","description":"Learning Symmetric and Low-energy Locomotiondiscusses捕获点。"}},{"data":{"id":"rel_ent_principle_capture_point_mentions_ent_principle_zero_moment_point","source":"ent_principle_capture_point","target":"ent_principle_zero_moment_point","type":"mentions","description":"捕获点提及零力矩点（ZMP）。"}},{"data":{"id":"rel_ent_method_model_predictive_control_mentions_ent_principle_capture_point","source":"ent_method_model_predictive_control","target":"ent_principle_capture_point","type":"mentions","description":"模型预测控制（MPC）提及捕获点。"}},{"data":{"id":"rel_ent_paper_learning_humanoid_arm_motion_v_2025_discusses_ent_principle_capture_point","source":"ent_paper_learning_humanoid_arm_motion_v_2025","target":"ent_principle_capture_point","type":"discusses","description":"Learning Humanoid Arm Motion via Centroidal Momentum Regularized Multi-Agent Reinforcement Learningdiscusses捕获点。"}},{"data":{"id":"rel_ent_paper_end_to_end_humanoid_robot_safe_2025_mentions_ent_principle_capture_point","source":"ent_paper_end_to_end_humanoid_robot_safe_2025","target":"ent_principle_capture_point","type":"mentions","description":"End-to-End Humanoid Robot Safe and Comfortable Locomotion Policy提及捕获点。"}},{"data":{"id":"rel_ent_paper_architecture_is_all_you_need_d_2025_uses_ent_principle_capture_point","source":"ent_paper_architecture_is_all_you_need_d_2025","target":"ent_principle_capture_point","type":"uses","description":"Architecture Is All You Need: Diversity-Enabled Sweet Spots for Robust Humanoid Locomotion使用捕获点。"}},{"data":{"id":"rel_ent_paper_shield_safety_on_humanoids_via_2025_discusses_ent_principle_capture_point","source":"ent_paper_shield_safety_on_humanoids_via_2025","target":"ent_principle_capture_point","type":"discusses","description":"SHIELD: Safety on Humanoids via CBFs In Expectation on Learned Dynamicsdiscusses捕获点。"}},{"data":{"id":"rel_ent_principle_capture_point_mentions_ent_method_gait_planning","source":"ent_principle_capture_point","target":"ent_method_gait_planning","type":"mentions","description":"捕获点提及步态规划。"}},{"data":{"id":"rel_ent_method_fea_finite_element_analysis_mentions_ent_principle_capture_point","source":"ent_method_fea_finite_element_analysis","target":"ent_principle_capture_point","type":"mentions","description":"同一 Wiki 章节中共同出现的关系。"}},{"data":{"id":"rel_ent_formalism_floating_base_dynamics_mentions_ent_principle_capture_point","source":"ent_formalism_floating_base_dynamics","target":"ent_principle_capture_point","type":"mentions","description":"同一 Wiki 章节中共同出现的关系。"}},{"data":{"id":"rel_ent_method_inverse_kinematics_mentions_ent_principle_capture_point","source":"ent_method_inverse_kinematics","target":"ent_principle_capture_point","type":"mentions","description":"同一 Wiki 章节中共同出现的关系。"}},{"data":{"id":"rel_ent_principle_zero_moment_point_mentions_ent_principle_capture_point","source":"ent_principle_zero_moment_point","target":"ent_principle_capture_point","type":"mentions","description":"同一 Wiki 章节中共同出现的关系。"}},{"data":{"id":"rel_ent_method_forward_kinematics_mentions_ent_principle_capture_point","source":"ent_method_forward_kinematics","target":"ent_principle_capture_point","type":"mentions","description":"同一 Wiki 章节中共同出现的关系。"}}],"center_id":"ent_principle_capture_point"}