{"nodes":[{"data":{"id":"ent_algorithm_ppo","name":"근위 정책 최적화(PPO)","type":"algorithm","domains":["07_ai_models_algorithms"]}},{"data":{"id":"ent_paper_dreamcontrol_human_inspired_wh_2025","name":"DreamControl: Human-Inspired Whole-Body Humanoid Control for Scene Interaction via Guided Diffusion","type":"paper","domains":["07_ai_models_algorithms"]}}],"edges":[{"data":{"id":"rel_ent_paper_dreamcontrol_human_inspired_wh_2025_mentions_ent_algorithm_ppo","source":"ent_paper_dreamcontrol_human_inspired_wh_2025","target":"ent_algorithm_ppo","type":"mentions","description":"DreamControl: Human-Inspired Whole-Body Humanoid Control for Scene Interaction via Guided Diffusion mentions Proximal Policy Optimization (PPO)."}}],"center_id":"ent_paper_dreamcontrol_human_inspired_wh_2025"}